MANIFEST.in
README.md
setup.cfg
setup.py
atiim/__init__.py
atiim/dem.py
atiim/gage.py
atiim/hypsometric.py
atiim/inflection.py
atiim/inundation.py
atiim/logger.py
atiim/package_data.py
atiim/plots.py
atiim.egg-info/PKG-INFO
atiim.egg-info/SOURCES.txt
atiim.egg-info/dependency_links.txt
atiim.egg-info/requires.txt
atiim.egg-info/top_level.txt
atiim/data/basin_1.cpg
atiim/data/basin_1.dbf
atiim/data/basin_1.prj
atiim/data/basin_1.shp
atiim/data/basin_1.shx
atiim/data/dem.mgrd
atiim/data/dem.prj
atiim/data/dem.sdat
atiim/data/dem.sdat.aux.xml
atiim/data/dem.sgrd
atiim/data/gage_location_1.cpg
atiim/data/gage_location_1.dbf
atiim/data/gage_location_1.prj
atiim/data/gage_location_1.shp
atiim/data/gage_location_1.shx
atiim/data/water_level.csv
atiim/tests/__init__.py
atiim/tests/test_dem.py