Metadata-Version: 2.1
Name: atiim
Version: 0.0.0
Summary: The Area Time Inundation Index Model
Home-page: https://github.com/crvernon/atiim
Author: André M. Coleman; Chris R. Vernon
License: BSD-2-Clause
Platform: UNKNOWN
Requires-Python: >=3.7.*, <4
Provides-Extra: dev
